[
  {
    "id": 1,
    "page": 1,
    "img": "img/list-1.jpg",
    "desc": "2017年2月2日我们恋爱了，爱情的滋味很奇妙."
  },
  {
    "id": 2,
    "page": 1,
    "img": "img/list-2.jpg",
    "desc": "很长一段时间，我们天天吵架，我那时候天天写日记吐槽她，她也天天看，嘻嘻哈哈中，我们都在改变."
  },
  {
    "id": 3,
    "page": 1,
    "img": "img/list-3.jpg",
    "desc": "我们每天晚上都会散步，讨论今天，讨论明天，讨论未来."
  },
  {
    "id": 4,
    "page": 1,
    "img": "img/login-bg.jpg",
    "desc": "时而甜到齁，时而苦到痛，亦步亦趋，我们在慢慢成长着."
  },
  {
    "id": 5,
    "page": 1,
    "img": "img/list-5.jpg",
    "desc": "赵旭，我很爱你...旁边的心心都是爱你的形状哦，哈哈！"
  },
  {
    "id": 6,
    "page": 2,
    "img": "img/list-6.jpg",
    "desc": "我们会一直走下去，走下去..."
  },
  {
    "id": 7,
    "page": 2,
    "img": "img/list-6.jpg",
    "desc": "我们会一直走下去，走下去..."
  },
  {
    "id": 8,
    "page": 2,
    "img": "img/list-6.jpg",
    "desc": "我们会一直走下去，走下去..."
  },
  {
    "id": 9,
    "page": 2,
    "img": "img/list-6.jpg",
    "desc": "我们会一直走下去，走下去..."
  },
  {
    "id": 10,
    "page": 2,
    "img": "img/list-6.jpg",
    "desc": "我们会一直走下去，走下去..."
  },
  {
    "id": 11,
    "page": 3,
    "img": "img/list-6.jpg",
    "desc": "我们会一直走下去，走下去..."
  },
  {
    "id": 12,
    "page": 3,
    "img": "img/list-6.jpg",
    "desc": "我们会一直走下去，走下去..."
  },
  {
    "id": 13,
    "page": 3,
    "img": "img/list-6.jpg",
    "desc": "我们会一直走下去，走下去..."
  },
  {
    "id": 14,
    "page": 3,
    "img": "img/list-6.jpg",
    "desc": "我们会一直走下去，走下去..."
  },
  {
    "id": 15,
    "page": 3,
    "img": "img/list-6.jpg",
    "desc": "我们会一直走下去，走下去..."
  }
]